rtdpy/__init__.py
rtdpy/_version.py
rtdpy/ad_cc.py
rtdpy/ad_cc_funcs.py
rtdpy/ad_hi_peclet.py
rtdpy/ad_oo.py
rtdpy/arbitrary.py
rtdpy/const.py
rtdpy/convection.py
rtdpy/elist.py
rtdpy/ncstr.py
rtdpy/pfr.py
rtdpy/rtd.py
rtdpy/zusatz.py
rtdpy-0.6.1.dist-info/licenses/LICENSE
rtdpy-0.6.1.dist-info/licenses/LICENSES_THIRD_PARTY
rtdpy-0.6.1.dist-info/METADATA
rtdpy-0.6.1.dist-info/WHEEL
rtdpy-0.6.1.dist-info/top_level.txt
rtdpy-0.6.1.dist-info/RECORD
