Metadata-Version: 2.4
Name: rtdpy
Version: 0.6.1
Summary: Python package for residence time distribution analysis
Author-email: Matthew Flamm <matthew.flamm@merck.com>
License: MIT
Project-URL: Homepage, https://merck.github.io/rtdpy
Project-URL: Repository, https://github.com/Merck/rtdpy
Project-URL: Documentation, https://merck.github.io/rtdpy
Classifier: Development Status :: 4 - Beta
Classifier: Programming Language :: Python :: 3
Classifier: Programming Language :: Python :: 3.10
Classifier: Programming Language :: Python :: 3.11
Classifier: Programming Language :: Python :: 3.12
Classifier: Programming Language :: Python :: 3.13
Classifier: Programming Language :: Python :: 3.14
Classifier: License :: OSI Approved :: MIT License
Classifier: Topic :: Scientific/Engineering
Requires-Python: >=3.10
License-File: LICENSE
License-File: LICENSES_THIRD_PARTY
Requires-Dist: numpy>=1.23.0
Requires-Dist: scipy>=1.9.0
Provides-Extra: dev
Requires-Dist: numpy==2.3.5; extra == "dev"
Requires-Dist: scipy==1.16.3; extra == "dev"
Requires-Dist: pytest>=7.0; extra == "dev"
Requires-Dist: pytest-cov>=4.0; extra == "dev"
Requires-Dist: ruff>=0.1.0; extra == "dev"
Provides-Extra: dev-min
Requires-Dist: numpy==1.23.0; extra == "dev-min"
Requires-Dist: scipy==1.9.0; extra == "dev-min"
Requires-Dist: pytest>=7.0; extra == "dev-min"
Requires-Dist: pytest-cov>=4.0; extra == "dev-min"
Requires-Dist: ruff>=0.1.0; extra == "dev-min"
Provides-Extra: docs
Requires-Dist: sphinx; extra == "docs"
Requires-Dist: numpydoc>=1.0.0; extra == "docs"
Requires-Dist: matplotlib; extra == "docs"
Requires-Dist: ipython; extra == "docs"
Dynamic: license-file
